{
	"name": "df_gold_dim_fecha",
	"properties": {
		"folder": {
			"name": "GOLD"
		},
		"type": "MappingDataFlow",
		"typeProperties": {
			"sources": [
				{
					"dataset": {
						"referenceName": "ds_sql_silver_llamadas",
						"type": "DatasetReference"
					},
					"name": "fechallamadas"
				},
				{
					"dataset": {
						"referenceName": "ds_sql_silver_datos",
						"type": "DatasetReference"
					},
					"name": "fechainicio"
				},
				{
					"dataset": {
						"referenceName": "ds_sql_silver_datos",
						"type": "DatasetReference"
					},
					"name": "fechafin"
				}
			],
			"sinks": [
				{
					"dataset": {
						"referenceName": "ds_gold_dim_fecha",
						"type": "DatasetReference"
					},
					"name": "sink1"
				}
			],
			"transformations": [
				{
					"name": "union1"
				},
				{
					"name": "union2"
				},
				{
					"name": "sort1"
				},
				{
					"name": "filter1"
				},
				{
					"name": "aggregate1"
				}
			],
			"scriptLines": [
				"source(output(",
				"          fecha as timestamp",
				"     ),",
				"     allowSchemaDrift: true,",
				"     validateSchema: false,",
				"     isolationLevel: 'READ_UNCOMMITTED',",
				"     query: 'select DISTINCT fecha from silver.llamadas',",
				"     format: 'query') ~> fechallamadas",
				"source(output(",
				"          fecha as timestamp",
				"     ),",
				"     allowSchemaDrift: true,",
				"     validateSchema: false,",
				"     isolationLevel: 'READ_UNCOMMITTED',",
				"     query: 'SELECT DISTINCT fecha_inicio as fecha from silver.datos',",
				"     format: 'query') ~> fechainicio",
				"source(output(",
				"          fecha as timestamp",
				"     ),",
				"     allowSchemaDrift: true,",
				"     validateSchema: false,",
				"     isolationLevel: 'READ_UNCOMMITTED',",
				"     query: '\\nselect distinct fecha_fin as fecha from silver.datos',",
				"     format: 'query') ~> fechafin",
				"fechallamadas, fechainicio union(byName: true)~> union1",
				"union1, fechafin union(byName: true)~> union2",
				"union2 sort(asc(fecha, true)) ~> sort1",
				"sort1 filter(!isNull(fecha)) ~> filter1",
				"filter1 aggregate(groupBy(fecha),",
				"     each(match(name != 'fecha'), $$ = first($$))) ~> aggregate1",
				"aggregate1 sink(allowSchemaDrift: true,",
				"     validateSchema: false,",
				"     input(",
				"          id_fecha as integer,",
				"          fecha as timestamp",
				"     ),",
				"     deletable:false,",
				"     insertable:true,",
				"     updateable:false,",
				"     upsertable:false,",
				"     format: 'table',",
				"     skipDuplicateMapInputs: true,",
				"     skipDuplicateMapOutputs: true,",
				"     errorHandlingOption: 'stopOnFirstError',",
				"     mapColumn(",
				"          fecha",
				"     )) ~> sink1"
			]
		}
	}
}